Metadata-Version: 2.4
Name: omnicart-pipeline-tegakay
Version: 0.1.4
Summary: 
Author: tegakay
Author-email: kofitega@gmail.com
Requires-Python: >=3.10
Classifier: Programming Language :: Python :: 3
Classifier: Programming Language :: Python :: 3.10
Classifier: Programming Language :: Python :: 3.11
Classifier: Programming Language :: Python :: 3.12
Classifier: Programming Language :: Python :: 3.13
Classifier: Programming Language :: Python :: 3.14
Requires-Dist: pandas (>=2.3.0,<3.0.0)
Requires-Dist: requests (>=2.32.5,<3.0.0)
